Workbook

Sheet Shell 
A2: Financial Statement SHELL PLC
A3: ($ in million)
B4: 2025 | C4: 2024 | D4: 2023
A5: Income Statament
A6: Revenue | B6: 273731 | C6: 289029 | D6: 323183
A7: Cost of sales | B7: =177194+21898 -> 199092 | C7: =188120+23379 -> 211499 | D7: =212883+25240 -> 238123
A8: Gross Profit | B8: =B6-B7 -> 74639 | C8: =C6-C7 -> 77530 | D8: =D6-D7 -> 85060
A9: Operating Expenses | B9: =(243975-B7-B11-B12) -> 14913 | C9: =(259107-C7-C11-C12) -> 15949 | D9: =(290556-D7-D11-D12) -> 16470
A10: Operating Profit/EBITDA | B10: =(B8-B9) -> 59726 | C10: =(C8-C9) -> 61581 | D10: =(D8-D9) -> 68590
A11: Interest Expense | B11: 4671 | C11: 4787 | D11: 4673
A12: Depreciation & Amortization | B12: 25299 | C12: 26872 | D12: 31290
A13: Income before Tax | B13: =(B10-B11-B12) -> 29756 | C13: =(C10-C11-C12) -> 29922 | D13: =(D10-D11-D12) -> 32627
A14: Tax | B14: 11637 | C14: 13401 | D14: 12991
A15: Net Income | B15: =B13-B14 -> 18119 | C15: =C13-C14 -> 16521 | D15: =D13-D14 -> 19636
A17: Balance Sheet
A18: Total Assets | B18: 370350 | C18: 387609 | D18: 406270
A19: Current Assets | B19: 107173 | C19: 127926 | D19: 134115
A20: Inventory | B20: 22216 | C20: 23426 | D20: 26019
A21: Trade Receivables | B21: 44597 | C21: 45860 | D21: 53273
A22: Cash | B22: 30216 | C22: 39110 | D22: 38774
A23: Total Debt Non Current | B23: 66515 | C23: 65448 | D23: 71610
A24: Total Debt Current | B24: 9128 | C24: 11630 | D24: 9931
A25: Trade & Other Payables | B25: 57770 | C25: 60693 | D25: 68237
A26: Total Current Liabilities | B26: 82415 | C26: 95034 | D26: 95467
A27: Total Non Current Liablities | B27: =B28-B26 -> 112616 | C27: =C28-C26 -> 112407 | D27: =D28-D26 -> 122441
A28: Total Liabilities | B28: 195031 | C28: 207441 | D28: 217908
A29: Total Equity | B29: 175319 | C29: 180168 | D29: 188362
A30: Total Debt | B30: =B23+B24 -> 75643 | C30: =C23+C24 -> 77078 | D30: =D23+D24 -> 81541
A31: Net Debt | B31: =B30-B22 -> 45427 | C31: =C30-C22 -> 37968 | D31: =D30-D22 -> 42767
A33: Cash Flow
A34: Operating Cash Flow | B34: 42863 | C34: 54687 | D34: 54191
A35: Cash flow from investing Activities | B35: -16811 | C35: -15155 | D35: -17734
A36: Cash flow from Financing Activities | B36: -35812 | C36: -38435 | D36: -38235
A37: Capex | B37: 20915 | C37: 21085 | D37: 24392

Sheet BP
A2: Financial Statement BP
A3: ($ in million)
B4: 2025 | C4: 2024 | D4: 2023
A5: Income Statement
A6: Revenue | B6: 192549 | C6: 194629 | D6: 213032
A7: Cost of sales | B7: =110640+25646 -> 136286 | C7: =113941+26584 -> 140525 | D7: =119307+25044 -> 144351
A8: Gross Profit | B8: =B6-B7 -> 56263 | C8: =C6-C7 -> 54104 | D8: =D6-D7 -> 68681
A9: Operating Expenses | B9: =(B6-12642-B12-B7) -> 25799 | C9: =(C6-11297-C12-C7) -> 26185 | D9: =(D6-27348-D12-D7) -> 25405
A10: Operating Profit/EBITDA | B10: =(B8-B9) -> 30464 | C10: =(C8-C9) -> 27919 | D10: =(D8-D9) -> 43276
A11: Interest Expense | B11: =5106+(-210) -> 4896 | C11: =4683+(-168) -> 4515 | D11: =3840+(-241) -> 3599
A12: Depreciation & Amortization | B12: 17822 | C12: 16622 | D12: 15928
A13: Income before Tax | B13: =(B10-B11-B12) -> 7746 | C13: =(C10-C11-C12) -> 6782 | D13: =(D10-D11-D12) -> 23749
A14: Tax | B14: 6451 | C14: 5553 | D14: 7869
A15: Net Income | B15: =B13-B14 -> 1295 | C15: =C13-C14 -> 1229 | D15: =D13-D14 -> 15880
A17: Balance Sheet
A18: Total Assets | B18: 278526 | C18: 282228 | D18: 280294
A19: Current Assets | B19: 101786 | C19: 102834 | D19: 104146
A20: Inventory | B20: 22499 | C20: 23232 | D20: 22819
A21: Trade Receivables | B21: 26014 | C21: 27127 | D21: 31123
A22: Cash | B22: 36556 | C22: 39204 | D22: 33030
A23: Total Debt Non Current | B23: 54602 | C23: 55073 | D23: 48670
A24: Total Debt Current | B24: =2832+3356 -> 6188 | C24: =2660+4474 -> 7134 | D24: =2650+3284 -> 5934
A25: Trade & Other Payables | B25: 56843 | C25: 58411 | D25: 61155
A26: Total Current Liabilities | B26: 80581 | C26: 82241 | D26: 86078
A27: Total Non Current Liablities | B27: =B28-B26 -> 123945 | C27: =C28-C26 -> 121669 | D27: =D28-D26 -> 108723
A28: Total Liabilities | B28: 204526 | C28: 203910 | D28: 194801
A29: Total Equity | B29: 74000 | C29: 78318 | D29: 85493
A30: Total Debt | B30: =B23+B24 -> 60790 | C30: =C23+C24 -> 62207 | D30: =D23+D24 -> 54604
A31: Net Debt | B31: =B30-B22 -> 24234 | C31: =C30-C22 -> 23003 | D31: =D30-D22 -> 21574
A33: Cash Flow
A34: Operating Cash Flow | B34: 24493 | C34: 27297 | D34: 32039
A35: Cash flow from investing Activities | B35: -11504 | C35: -13250 | D35: -14872
A36: Cash flow from Financing Activities | B36: -15880 | C36: -7297 | D36: -13359
A37: Capex | B37: 14533 | C37: 16237 | D37: 16253

Sheet Fianncial Analysis 
A3: Ratios | B3: SHELL PLC | E3: BP
B4: 2025 | C4: 2024 | D4: 2023 | E4: 2025 | F4: 2024 | G4: 2023
A5: Liquidity Ratios
A6: Current Ratio | B6: =('Shell '!B19/'Shell '!B26) -> 1.3004065 | C6: =('Shell '!C19/'Shell '!C26) -> 1.3461077 | D6: =('Shell '!D19/'Shell '!D26) -> 1.404831 | E6: =(BP!B19/BP!B26) -> 1.2631514 | F6: =(BP!C19/BP!C26) -> 1.2503982 | G6: =(BP!D19/BP!D26) -> 1.2099026
A7: Quick Ratio | B7: =('Shell '!B19-'Shell '!B20)/'Shell '!B26 -> 1.0308439 | C7: =('Shell '!C19-'Shell '!C20)/'Shell '!C26 -> 1.0996065 | D7: =('Shell '!D19-'Shell '!D20)/'Shell '!D26 -> 1.1322865 | E7: =(BP!B19-BP!B20)/BP!B26 -> 0.98394162 | F7: =(BP!C19-BP!C20)/BP!C26 -> 0.96791138 | G7: =(BP!D19-BP!D20)/BP!D26 -> 0.94480587
A9: Efficiency Ratio
A10: Inventory Days | B10: =IFERROR(365/('Shell '!B7/(('Shell '!B20+'Shell '!C20)/2)),"-") -> 41.838271 | C10: =IFERROR(365/('Shell '!C7/(('Shell '!C20+'Shell '!D20)/2)),"-") -> 42.665509 | D10: =IFERROR(365/('Shell '!D7/(('Shell '!D20+'Shell '!E20)/2)),"-") -> 19.941238 | E10: =IFERROR(365/(BP!B7/((BP!B20+BP!C20)/2)),"-") -> 61.238187 | F10: =IFERROR(365/(BP!C7/((BP!C20+BP!D20)/2)),"-") -> 59.806494 | G10: =IFERROR(365/(BP!D7/((BP!D20+BP!E20)/2)),"-") -> 28.849592
A11: Accounts Receivable Days | B11: =IFERROR(365/('Shell '!B6/(('Shell '!B21+'Shell '!C21)/2)),"-") -> 60.308852 | C11: =IFERROR(365/('Shell '!C6/(('Shell '!C21+'Shell '!D21)/2)),"-") -> 62.595008 | D11: =IFERROR(365/('Shell '!D6/(('Shell '!D21+'Shell '!E21)/2)),"-") -> 30.083026 | E11: =IFERROR(365/(BP!B6/((BP!B21+BP!C21)/2)),"-") -> 50.367608 | F11: =IFERROR(365/(BP!C6/((BP!C21+BP!D21)/2)),"-") -> 54.619944 | G11: =IFERROR(365/(BP!D6/((BP!D21+BP!E21)/2)),"-") -> 26.662415
A12: Accounts Payable Days | B12: =IFERROR(365/('Shell '!B7/(('Shell '!B25+'Shell '!C25)/2)),"-") -> 108.59049 | C12: =(('Shell '!C25+'Shell '!D25)/2)/(('Shell '!C7))*365 -> 111.25218 | D12: =(('Shell '!D25+'Shell '!E25)/2)/(('Shell '!D7))*365 -> 52.297563 | E12: =IFERROR(365/(BP!B7/((BP!B25+BP!C25)/2)),"-") -> 154.33614 | F12: =IFERROR(365/(BP!C7/((BP!C25+BP!D25)/2)),"-") -> 155.28052 | G12: =IFERROR(365/(BP!D7/((BP!D25+BP!E25)/2)),"-") -> 77.317009
A13: Cash Conversion Cycle | B13: =B10+B11-B12 -> -6.4433651 | C13: =C10+C11-C12 -> -5.991664 | D13: =D10+D11-D12 -> -2.2732985 | E13: =E10+E11-E12 -> -42.730344 | F13: =F10+F11-F12 -> -40.854082 | G13: =G10+G11-G12 -> -21.805002
A15: Leverage/ Solvency
A16: Debt to Equity | B16: ='Shell '!B30/'Shell '!B29 -> 0.43145923 | C16: ='Shell '!C30/'Shell '!C29 -> 0.42781182 | D16: ='Shell '!D30/'Shell '!D29 -> 0.43289517 | E16: =BP!B30/BP!B29 -> 0.82148649 | F16: =BP!C30/BP!C29 -> 0.79428739 | G16: =BP!D30/BP!D29 -> 0.63869557
A17: Debt to Assets | B17: ='Shell '!B30/'Shell '!B18 -> 0.20424733 | C17: ='Shell '!C30/'Shell '!C18 -> 0.19885503 | D17: ='Shell '!D30/'Shell '!D18 -> 0.20070643 | E17: =BP!B30/BP!B18 -> 0.21825611 | F17: =BP!C30/BP!C18 -> 0.22041399 | G17: =BP!D30/BP!D18 -> 0.19480974
A18: Net Debt to EBITDA | B18: ='Shell '!B31/'Shell '!B10 -> 0.76059003 | C18: ='Shell '!C31/'Shell '!C10 -> 0.61655381 | D18: ='Shell '!D31/'Shell '!D10 -> 0.62351655 | E18: =BP!B31/BP!B10 -> 0.79549632 | F18: =BP!C31/BP!C10 -> 0.82391919 | G18: =BP!D31/BP!D10 -> 0.49852112
A19: Interest Coverage Ratio | B19: =('Shell '!B10/'Shell '!B11) -> 12.786555 | C19: =('Shell '!C10/'Shell '!C11) -> 12.864216 | D19: =('Shell '!D10/'Shell '!D11) -> 14.677937 | E19: =BP!B10/BP!B11 -> 6.2222222 | F19: =BP!C10/BP!C11 -> 6.1836102 | G19: =BP!D10/BP!D11 -> 12.024451
A21: Profitability %
A22: GP Margin | B22: ='Shell '!B8/'Shell '!B6 -> 0.27267281 | C22: ='Shell '!C8/'Shell '!C6 -> 0.26824298 | D22: ='Shell '!D8/'Shell '!D6 -> 0.26319454 | E22: =BP!B8/BP!B6 -> 0.29220095 | F22: =BP!C8/BP!C6 -> 0.2779853 | G22: =BP!D8/BP!D6 -> 0.32239757
A23: EBITDA Margin | B23: ='Shell '!B10/'Shell '!B6 -> 0.21819231 | C23: ='Shell '!C10/'Shell '!C6 -> 0.21306167 | D23: ='Shell '!D10/'Shell '!D6 -> 0.2122327 | E23: =BP!B10/BP!B6 -> 0.15821427 | F23: =BP!C10/BP!C6 -> 0.14344728 | G23: =BP!D10/BP!D6 -> 0.20314319
A24: NP Margin | B24: ='Shell '!B15/'Shell '!B6 -> 0.066192722 | C24: ='Shell '!C15/'Shell '!C6 -> 0.057160354 | D24: ='Shell '!D15/'Shell '!D6 -> 0.060758146 | E24: =BP!B15/BP!B6 -> 0.0067255608 | F24: =BP!C15/BP!C6 -> 0.006314578 | G24: =BP!D15/BP!D6 -> 0.074542792
A25: Return on Assets | B25: ='Shell '!B15/'Shell '!B18 -> 0.048923991 | C25: ='Shell '!C15/'Shell '!C18 -> 0.042622849 | D25: ='Shell '!D15/'Shell '!D18 -> 0.04833239 | E25: =BP!B15/BP!B18 -> 0.0046494762 | F25: =BP!C15/BP!C18 -> 0.0043546353 | G25: =BP!D15/BP!D18 -> 0.056654798
A26: Return on Equity | B26: ='Shell '!B15/'Shell '!B29 -> 0.10334875 | C26: ='Shell '!C15/'Shell '!C29 -> 0.091697749 | D26: ='Shell '!D15/'Shell '!D29 -> 0.10424608 | E26: =BP!B15/BP!B29 -> 0.0175 | F26: =BP!C15/BP!C29 -> 0.015692433 | G26: =BP!D15/BP!D29 -> 0.1857462
A28: Cash Flow
A29: Op. Cash flow to Debt | B29: ='Shell '!B34/'Shell '!B30 -> 0.5666486 | C29: ='Shell '!C34/'Shell '!C30 -> 0.70950206 | D29: ='Shell '!D34/'Shell '!D30 -> 0.66458591 | E29: =BP!B34/BP!B30 -> 0.40291166 | F29: =BP!C34/BP!C30 -> 0.43880914 | G29: =BP!D34/BP!D30 -> 0.58675189
A30: Free Cash Flow | B30: ='Shell '!B34-'Shell '!B37 -> 21948 | C30: ='Shell '!C34-'Shell '!C37 -> 33602 | D30: ='Shell '!D34-'Shell '!D37 -> 29799 | E30: =BP!B34-BP!B37 -> 9960 | F30: =BP!C34-BP!C37 -> 11060 | G30: =BP!D34-BP!D37 -> 15786
A31: Capex to Revenue | B31: ='Shell '!B37/'Shell '!B6 -> 0.07640713 | C31: ='Shell '!C37/'Shell '!C6 -> 0.072951157 | D31: ='Shell '!D37/'Shell '!D6 -> 0.075474267 | E31: =BP!B37/BP!B6 -> 0.075476892 | F31: =BP!C37/BP!C6 -> 0.083425389 | G31: =BP!D37/BP!D6 -> 0.076293702
A33: EBITDA Trend | B33: 59726 | C33: 61581 | D33: 68590 | E33: 30464 | F33: 27919 | G33: 43276
A34: DSCR | B34: ='Fianncial Analysis '!B33/('Shell '!B11+'Shell '!B24) -> 4.3282847 | C34: ='Fianncial Analysis '!C33/('Shell '!C11+'Shell '!C24) -> 3.7510507 | D34: ='Fianncial Analysis '!D33/('Shell '!D11+'Shell '!D24) -> 4.6966584 | E34: =E33/(BP!B11+BP!B24) -> 2.7484663 | F34: =F33/(BP!C11+BP!C24) -> 2.3966864 | G34: =G33/(BP!D11+BP!D24) -> 4.5395993

Sheet Risk Scorecard
A3: Category | B3: Weight | C3: Ratio | D3: Shell 2025 | E3: Score (1-5) | F3: Weighted Score | G3: BP 2025 | H3: Score (1-5) | I3: Weighted Score | N3: Risk Grade Tables
A4: Liquidity | B4: 0.2 | N4: Total Score | O4: Grade | P4: Stage
B5: Current Ratio | D5: ='Fianncial Analysis '!B6 -> 1.3004065 | E5: =IF(D5>=1.5,5,IF(D5>=1.25,4,IF(D5>=1,3,IF(D5>=0.75,2,1)))) -> 4 | F5: =E5*(B4/2) -> 0.4 | G5: ='Fianncial Analysis '!E6 -> 1.2631514 | H5: =IF(G5>=1.5,5,IF(G5>=1.25,4,IF(G5>=1,3,IF(G5>=0.75,2,1)))) -> 4 | I5: =H5*(B4/2) -> 0.4 | N5: 80-100 | O5: AAA-AA | P5: Stage 1
B6: Quick Ratio | D6: ='Fianncial Analysis '!B7 -> 1.0308439 | E6: =IF(D6>=1.25,5,IF(D6>=1,4,IF(D6>=0.75,3,IF(D6>=0.5,2,1)))) -> 4 | F6: =E6*(B4/2) -> 0.4 | G6: ='Fianncial Analysis '!E7 -> 0.98394162 | H6: =IF(G6>=1.25,5,IF(G6>=1,4,IF(G6>=0.75,3,IF(G6>=0.5,2,1)))) -> 3 | I6: =H6*(B4/2) -> 0.3 | N6: 65-79 | O6: A-BBB | P6: Stage 1
A7: Leverage | B7: 0.25 | N7: 50-64 | O7: BB | P7: Stage 2
B8: Debt to Equity | D8: ='Fianncial Analysis '!B16 -> 0.43145923 | E8: =IF(D8<0.3,5,IF(D8<0.5,4,IF(D8<0.75,3,IF(D8<1,2,1)))) -> 4 | F8: =(E8*(B7/2)) -> 0.5 | G8: ='Fianncial Analysis '!E16 -> 0.82148649 | H8: =IF(G8<0.3,5,IF(G8<0.5,4,IF(G8<0.75,3,IF(G8<1,2,1)))) -> 2 | I8: =(H8*(B7/2)) -> 0.25 | N8: 35-49 | O8: B | P8: Stage 2/3
B9: Net Debt/EBITDA | D9: ='Fianncial Analysis '!B18 -> 0.76059003 | E9: =IF(D9<0.5,5,IF(D9<1,4,IF(D9<2,3,IF(D9<3,2,1)))) -> 4 | F9: =E9*(B7/2) -> 0.5 | G9: ='Fianncial Analysis '!E18 -> 0.79549632 | H9: =IF(G9<0.5,5,IF(G9<1,4,IF(G9<2,3,IF(G9<3,2,1)))) -> 4 | I9: =H9*(B7/2) -> 0.5 | N9: Below 35 | O9: CCC-D | P9: Stage 3
A10: Profitability | B10: 0.2
B11: EBITDA Margin | D11: ='Fianncial Analysis '!B23 -> 0.21819231 | E11: =IF(D11>=0.25,5,IF(D11>=0.2,4,IF(D11>=0.15,3,IF(D11>=0.1,2,1)))) -> 4 | F11: =(E11*(B10/2)) -> 0.4 | G11: ='Fianncial Analysis '!E23 -> 0.15821427 | H11: =IF(G11>=0.25,5,IF(G11>=0.2,4,IF(G11>=0.15,3,IF(G11>=0.1,2,1)))) -> 3 | I11: =(H11*(B10/2)) -> 0.3 | N11: PD Table:
B12: ROE | D12: ='Fianncial Analysis '!B26 -> 0.10334875 | E12: =IF(D12>=0.15,5,IF(D12>=0.1,4,IF(D12>=0.05,3,IF(D12>=0.01,2,1)))) -> 4 | F12: =(E12*(B10/2)) -> 0.4 | G12: ='Fianncial Analysis '!E26 -> 0.0175 | H12: =IF(G12>=0.15,5,IF(G12>=0.1,4,IF(G12>=0.05,3,IF(G12>=0.01,2,1)))) -> 2 | I12: =(H12*(B10/2)) -> 0.2 | N12: Grade | O12: PD
A13: Debt Service | B13: 0.25 | N13: AAA-AA | O13: 0.0003
B14: DSCR | D14: ='Fianncial Analysis '!B34 -> 4.3282847 | E14: =IF(D14>=3,5,IF(D14>=2,4,IF(D14>=1.5,3,IF(D14>=1,2,1)))) -> 5 | F14: =(E14*(B13/2)) -> 0.625 | G14: ='Fianncial Analysis '!E34 -> 2.7484663 | H14: =IF(G14>=3,5,IF(G14>=2,4,IF(G14>=1.5,3,IF(G14>=1,2,1)))) -> 4 | I14: =(H14*(B13/2)) -> 0.5 | N14: A-BBB | O14: 0.0015
B15: Int. Coverage | D15: ='Fianncial Analysis '!B19 -> 12.786555 | E15: =IF(D15>=10,5,IF(D15>=7,4,IF(D15>=5,3,IF(D15>=3,2,1)))) -> 5 | F15: =(E15*(B13/2)) -> 0.625 | G15: ='Fianncial Analysis '!E19 -> 6.2222222 | H15: =IF(G15>=10,5,IF(G15>=7,4,IF(G15>=5,3,IF(G15>=3,2,1)))) -> 3 | I15: =(H15*(B13/2)) -> 0.375 | N15: BB | O15: 0.02
A16: Efficiency | B16: 0.1 | N16: B | O16: 0.08
B17: OCF to Debt | D17: ='Fianncial Analysis '!B29 -> 0.5666486 | E17: =IF(D17>=0.6,5,IF(D17>=0.4,4,IF(D17>=0.2,3,IF(D17>=0.1,2,1)))) -> 4 | F17: =(E17*(B16/2)) -> 0.2 | G17: ='Fianncial Analysis '!E29 -> 0.40291166 | H17: =IF(G17>=0.6,5,IF(G17>=0.4,4,IF(G17>=0.2,3,IF(G17>=0.1,2,1)))) -> 4 | I17: =(H17*(B16/2)) -> 0.2 | N17: CCC-D | O17: 0.2
B18: CCC | D18: ='Fianncial Analysis '!B13 -> -6.4433651 | E18: =IF(D18<0,5,IF(D18<=30,3,1)) -> 5 | F18: =(E18*(B16/2)) -> 0.25 | G18: ='Fianncial Analysis '!E13 -> -42.730344 | H18: =IF(G18<0,5,IF(G18<=30,3,1)) -> 5 | I18: =(H18*(B16/2)) -> 0.25
A19: Total | B19: =B4+B7+B10+B13+B16 -> 1 | E19: =SUM(E5:E18) -> 43 | F19: =SUM(F5:F18) -> 4.3 | H19: =SUM(H5:H18) -> 34 | I19: =SUM(I5:I18) -> 3.275 | N19: Score Table
A20: Risk Score (out of 100) | F20: =(F19/5)*100 -> 86 | I20: =(I19/5)*100 -> 65.5 | N20: 5 | O20: Excellent
A21: Risk Grade | F21: =IF(F20>=80,"AAA-AA",IF(F20>=65,"A-BBB",IF(F20>=50,"BB",IF(F20>=35,"B","CCC-D")))) -> AAA-AA | I21: =IF(I20>=80,"AAA-AA",IF(I20>=65,"A-BBB",IF(I20>=50,"BB",IF(I20>=35,"B","CCC-D")))) -> A-BBB | N21: 4 | O21: Good
A22: IFRS 9 Stage | F22: =IF(F20>=65,"Stage 1",IF(F20>=50,"Stage 2",IF(F20>=35,"Stage 2/3","Stage 3"))) -> Stage 1 | I22: =IF(I20>=65,"Stage 1",IF(I20>=50,"Stage 2",IF(I20>=35,"Stage 2/3","Stage 3"))) -> Stage 1 | N22: 3 | O22: Satisfactory
A23: PD | F23: =O13 -> 0.0003 | I23: =O14 -> 0.0015 | N23: 2 | O23: Weak
N24: 1 | O24: Poor

Sheet ECL
A2: Expected Credit Loss (ECL) | B2: Non Funded | D2: Funded | I2: Facility Structure | K2: USD in Million
B3: Shell | C3: BP | D3: Shell | E3: BP | K3: Shell | L3: BP
A4: Facility Type | B4: LC Sight Facility | C4: LC Sight Facility | D4: Term Loan | E4: Term Loan | I4: Non Funded Lines
A5: Facility Limit (USD) | B5: 500 | C5: 300 | D5: 300 | E5: 200 | I5: LC Sight | K5: 500 | L5: 300
A6: Utilisation % | B6: =K6 -> 0.8 | C6: =L6 -> 0.85 | D6: =K9 -> 1 | E6: =L9 -> 0.9 | I6: Utilisation | K6: 0.8 | L6: 0.85
A7: Drawn Amount | B7: =B5*B6 -> 400 | C7: =C5*C6 -> 255 | D7: =D5*D6 -> 300 | E7: =E5*E6 -> 180 | I7: Funded
A8: Undrawn Amount | B8: =B5-B7 -> 100 | C8: =C5-C7 -> 45 | D8: =D5-D7 -> 0 | E8: =E5-E7 -> 20 | I8: Term Loan (5 year) | K8: 300 | L8: 200
A9: CCF | B9: 0.2 | C9: 0.2 | D9: 1 | E9: 1 | I9: Utilisation | K9: 1 | L9: 0.9
A10: EAD | B10: =(B7+(B8*B9)) -> 420 | C10: =(C7+(C8*C9)) -> 264 | D10: =(D7+(D8*D9)) -> 300 | E10: =(E7+(E8*E9)) -> 200
I11: Key parameters (Assumptions)
A12: IFRS 9 Stage | B12: ='Risk Scorecard'!F22 -> Stage 1 | C12: ='Risk Scorecard'!I22 -> Stage 1 | D12: ='Risk Scorecard'!F22 -> Stage 1 | E12: ='Risk Scorecard'!I22 -> Stage 1
A13: Risk Grade | B13: ='Risk Scorecard'!F21 -> AAA-AA | C13: ='Risk Scorecard'!I21 -> A-BBB | D13: AAA-AA | E13: A-BBB | J13: LC Sight | K13: Term Loan
A14: PD | B14: ='Risk Scorecard'!F23 -> 0.0003 | C14: ='Risk Scorecard'!I23 -> 0.0015 | D14: 0.0003 | E14: 0.0015 | I14: CCF (Basel III) | J14: 0.2 | K14: 1
A15: LGD | B15: 0.2 | C15: 0.2 | D15: 0.4 | E15: 0.45 | I15: LGD | J15: 0.25 | K15: 0.4
I16: Tenor | J16: 1 year | K16: 5 years
A17: ECL USD M | B17: =B10*B14*B15 -> 0.0252 | C17: =C10*C14*C15 -> 0.0792 | D17: =D10*D14*D15 -> 0.036 | E17: =E10*E14*E15 -> 0.135 | I17: PD basis | J17: 12-month | K17: 12-month (Stage 1)
A18: ECL % Facility | B18: =B17/B5 -> 5.04e-05 | C18: =C17/C5 -> 0.000264 | D18: =D17/D5 -> 0.00012 | E18: =E17/E5 -> 0.000675
I19: Facility | J19: Security | K19: Rationale
I20: LC Sight | J20: Lien over shipping/import documents | K20: UCP 600 — bank controls documents until retirement
A21: Total ECL Summary | I21: Term Loan Shell | J21: Unsecured + Negative Pledge | K21: Investment grade AAA-AA, market standard
A22: Total Non Funded ECL | B22: =B17 -> 0.0252 | C22: =C17 -> 0.0792 | I22: Term Loan BP | J22: Unsecured + Negative Pledge + Financial Covenants | K22: A-BBB borderline — additional covenant protection appropriate
A23: Total Funded ECL | B23: =D17 -> 0.036 | C23: =E17 -> 0.135
A24: Total ECL | B24: =B22+B23 -> 0.0612 | C24: =C22+C23 -> 0.2142 | I24: LGD update
A25: Exposure Funded | B25: =D5 -> 300 | C25: =E5 -> 200 | I25: Facility | J25: LGD | K25: Rationale
A26: Exposure Non Funded | B26: =B5 -> 500 | C26: =C5 -> 300 | I26: LC Sight | J26: 0.2 | K26: Document lien reduces loss — bank controls title document
A27: Total Exposure | B27: =B25+B26 -> 800 | C27: =C25+C26 -> 500 | I27: Term Loan Shell | J27: 0.4 | K27: Unsecured, investment grade, strong recovery expectation
A28: ECL % of Total Exposure | B28: =B24/B27 -> 7.65e-05 | C28: =C24/C27 -> 0.0004284 | I28: Term Loan BP | J28: 0.45 | K28: Unsecured, borderline grade, slightly higher loss assumption
A29: Total Portfolio ECL | B29: =B24+C24 -> 0.2754
I30: Glossary:
I31: PD | J31: Probability to Default
I32: ECL | J32: Expected Credit Loss
I33: LGD | J33: Loss Given Default
I34: EAD | J34: Exposure at Default
I35: CCF | J35: Credit Conversion Factor
I36: IFRS | J36: International Financial Reporting Standard
I38: Note: Risk Grade Tables & PD tables, references based on Moody's credit available on google.

Sheet Ratio Threshold Score Card
A3: Current Ratio: | D3: Quick Ratio:
A5: 5 | B5: >1.5x | D5: 5 | E5: > 1.25x
A6: 4 | B6: 1.25–1.5x | D6: 4 | E6: 1.0–1.25x
A7: 3 | B7: 1.0–1.25x | D7: 3 | E7: 0.75–1.0x
A8: 2 | B8: 0.75–1.0x | D8: 2 | E8: 0.5–0.75x
A9: 1 | B9: < 0.75x | D9: 1 | E9: < 0.5x
A13: Debt to Equity: | D13: Net Debt/EBITDA:
A15: 5 | B15: < 0.3x | D15: 5 | E15: <0.5x
A16: 4 | B16: 0.3–0.5x | D16: 4 | E16: 0.5–1.0x
A17: 3 | B17: 0.5–0.75x | D17: 3 | E17: 1.0–2.0x
A18: 2 | B18: 0.75–1.0x | D18: 2 | E18: 2.0–3.0x
A19: 1 | B19: > 1.0x | D19: 1 | E19: >3.0x
A22: EBITDA Margin: | D22: ROE:
A24: 5 | B24: >25% | D24: 5 | E24: >15%
A25: 4 | B25: 20–25% | D25: 4 | E25: 10–15%
A26: 3 | B26: 15–20% | D26: 3 | E26: 5–10%
A27: 2 | B27: 10–15% | D27: 2 | E27: 1–5%
A28: 1 | B28: <10% | D28: 1 | E28: <1% or negative
A31: DSCR: | D31: Interest Coverage:
A33: 5 | B33: > 3.0x | D33: 5 | E33: >10x
A34: 4 | B34: 2.0–3.0x | D34: 4 | E34: 7–10x
A35: 3 | B35: 1.5–2.0x | D35: 3 | E35: 5–7x
A36: 2 | B36: 1.0–1.5x | D36: 2 | E36: 3–5x
A37: 1 | B37: < 1.0x | D37: 1 | E37: < 3x
A40: OCF to Debt: | D40: CCC (negative is good for oil & gas):
A42: 5 | B42: >0.6x | D42: 5 | E42: negative
A43: 4 | B43: 0.4–0.6x | D43: 3 | E43: 0–30 days
A44: 3 | B44: 0.2–0.4x | D44: 1 | E44: >30 days
A45: 2 | B45: 0.1–0.2x
A46: 1 | B46: <0.1x

Sheet Stress Test
A2: Stress Testing Macro Economic Scenario
A3: Shell PLC | H3: BP
B4: Base Case | C4: =' Stress Test Assump'!C3 -> Scenario 1 High Oil | D4: =' Stress Test Assump'!D3 -> Scenario 2 Low Oil | E4: =' Stress Test Assump'!E3 -> Scenario 3 Cost pressure | F4: =' Stress Test Assump'!F3 -> Scenario 4 Combined Severe | H4: Base Case | I4: Scenario 1 High Oil | J4: Scenario 2 Low Oil | K4: Scenario 3 Cost pressure | L4: Scenario 4 Combined Severe
A5: Oil Price ($/bbl) | B5: =' Stress Test Assump'!B4 -> 75 | C5: =' Stress Test Assump'!C4 -> 144 | D5: =' Stress Test Assump'!D4 -> 60 | E5: =' Stress Test Assump'!E4 -> 90 | F5: =' Stress Test Assump'!F4 -> 67 | H5: 75 | I5: 144 | J5: 60 | K5: 90 | L5: 67
A6: Revenue Change % | B6: =' Stress Test Assump'!B5 -> 0 | C6: =' Stress Test Assump'!C5 -> 0.15 | D6: =' Stress Test Assump'!D5 -> -0.2 | E6: -0.05 | F6: -0.25 | H6: 0 | I6: 0.15 | J6: -0.2 | K6: -0.05 | L6: -0.25
A7: Cost Change % | B7: =' Stress Test Assump'!B6 -> 0 | C7: =' Stress Test Assump'!C6 -> 0.2 | D7: =' Stress Test Assump'!D6 -> -0.1 | E7: =' Stress Test Assump'!E6 -> 0.15 | F7: =' Stress Test Assump'!F6 -> 0.2 | H7: 0 | I7: 0.2 | J7: -0.1 | K7: 0.15 | L7: 0.2
A8: Interest Rate Change (bps) | B8: =' Stress Test Assump'!B7 -> 0 | C8: =' Stress Test Assump'!C7 -> 0 | D8: =' Stress Test Assump'!D7 -> 0 | E8: =' Stress Test Assump'!E7 -> 150 | F8: =' Stress Test Assump'!F7 -> 200 | H8: 0 | I8: 0 | J8: 0 | K8: 150 | L8: 200
A9: Freight/OpEx Change % | B9: =' Stress Test Assump'!B8 -> 0 | C9: =' Stress Test Assump'!C8 -> 0.1 | D9: =' Stress Test Assump'!D8 -> 0 | E9: =' Stress Test Assump'!E8 -> 0.3 | F9: =' Stress Test Assump'!F8 -> 0.35 | H9: 0 | I9: 0.1 | J9: 0 | K9: 0.3 | L9: 0.35
A10: FX Hedge Coverage % | B10: =' Stress Test Assump'!B9 -> 0.5 | C10: =' Stress Test Assump'!C9 -> 0.5 | D10: =' Stress Test Assump'!D9 -> 0.5 | E10: =' Stress Test Assump'!E9 -> 0.5 | F10: =' Stress Test Assump'!F9 -> 0.5 | H10: 0.5 | I10: 0.5 | J10: 0.5 | K10: 0.5 | L10: 0.5
A12: Base Revenue | B12: ='Shell '!B6 -> 273731 | C12: 273731 | D12: 273731 | E12: 273731 | F12: 273731 | H12: =BP!B6 -> 192549 | I12: 192549 | J12: 192549 | K12: 192549 | L12: 192549
A13: Stressed Revenue | B13: =B12*(1+B6) -> 273731 | C13: =C12*(1+C6) -> 314790.65 | D13: =D12*(1+D6) -> 218984.8 | E13: =E12*(1+E6) -> 260044.45 | F13: =F12*(1+F6) -> 205298.25 | H13: =H12*(1+H6) -> 192549 | I13: =I12*(1+I6) -> 221431.35 | J13: =J12*(1+J6) -> 154039.2 | K13: =K12*(1+K6) -> 182921.55 | L13: =L12*(1+L6) -> 144411.75
A14: Base EBITDA | B14: ='Shell '!B10 -> 59726 | C14: 59726 | D14: 59726 | E14: 59726 | F14: 59726 | H14: =BP!B10 -> 30464 | I14: 30464 | J14: 30464 | K14: 30464 | L14: 30464
A15: Stressed EBITDA | B15: =B14*(1+B6)*(1-(B7+B9)) -> 59726 | C15: =C14*(1+C6)*(1-(C7+C9)) -> 48079.43 | D15: =D14*(1+D6)*(1-(D7+D9)) -> 52558.88 | E15: =E14*(1+E6)*(1-(E7+E9)) -> 31206.835 | F15: =F14*(1+F6)*(1-(F7+F9)) -> 20157.525 | H15: =H14*(1+H6)*(1-(H7+H9)) -> 30464 | I15: =I14*(1+I6)*(1-(I7+I9)) -> 24523.52 | J15: =J14*(1+J6)*(1-(J7+J9)) -> 26808.32 | K15: =K14*(1+K6)*(1-(K7+K9)) -> 15917.44 | L15: =L14*(1+L6)*(1-(L7+L9)) -> 10281.6
A16: Base Interest Expense | B16: ='Shell '!B11 -> 4671 | C16: 4671 | D16: 4671 | E16: 4671 | F16: 4671 | H16: =BP!B11 -> 4896 | I16: 4896 | J16: 4896 | K16: 4896 | L16: 4896
A17: Stressed Interest Expense | B17: =B16 -> 4671 | C17: =C16 -> 4671 | D17: =D16 -> 4671 | E17: =E16*(1+(E8/1000*0.5)) -> 5021.325 | F17: =F16*(1+(F8/1000*0.5)) -> 5138.1 | H17: =H16 -> 4896 | I17: =I16 -> 4896 | J17: =J16 -> 4896 | K17: =K16*(1+(K8/1000*0.5)) -> 5263.2 | L17: =L16*(1+(L8/1000*0.5)) -> 5385.6
A18: Stressed DSCR | B18: =B15/(B17+'Fianncial Analysis '!B34) -> 12.774718 | C18: =C15/(C17+'Fianncial Analysis '!C34) -> 10.284918 | D18: =D15/(D17+'Fianncial Analysis '!D34) -> 11.240866 | E18: =E15/(E17+'Fianncial Analysis '!E34) -> 6.2114607 | F18: =F15/(F17+'Fianncial Analysis '!F34) -> 3.9213185 | H18: =H15/(H17+'Fianncial Analysis '!E34) -> 6.2187312 | I18: =I15/(I17+'Fianncial Analysis '!F34) -> 5.0064381 | J18: =J15/(J17+'Fianncial Analysis '!G34) -> 5.4704833 | K18: =K15/(K17+'Fianncial Analysis '!H34) -> 3.0242894 | L18: =L15/(L17+'Fianncial Analysis '!I34) -> 1.9090909
A19: Stressed ICR | B19: =B15/B17 -> 12.786555 | C19: =C15/C17 -> 10.293177 | D19: =D15/D17 -> 11.252169 | E19: =E15/E17 -> 6.2148606 | F19: =F15/F17 -> 3.9231477 | H19: =H15/H17 -> 6.2222222 | I19: =I15/I17 -> 5.0088889 | J19: =J15/J17 -> 5.4755556 | K19: =K15/K17 -> 3.0242894 | L19: =L15/L17 -> 1.9090909
A21: Stressed Risk Score | B21: =61+(IF(B17>=3,5,IF(B17>=2,4,IF(B17>=1.5,3,IF(B17>=1,2,1))))*0.125*20)+(IF(B18>=10,5,IF(B18>=7,4,IF(B18>=5,3,IF(B18>=3,2,1))))*0.125*20) -> 86 | C21: =61+(IF(C17>=3,5,IF(C17>=2,4,IF(C17>=1.5,3,IF(C17>=1,2,1))))*0.125*20)+(IF(C18>=10,5,IF(C18>=7,4,IF(C18>=5,3,IF(C18>=3,2,1))))*0.125*20) -> 86 | D21: =61+(IF(D17>=3,5,IF(D17>=2,4,IF(D17>=1.5,3,IF(D17>=1,2,1))))*0.125*20)+(IF(D18>=10,5,IF(D18>=7,4,IF(D18>=5,3,IF(D18>=3,2,1))))*0.125*20) -> 86 | E21: =61+(IF(E17>=3,5,IF(E17>=2,4,IF(E17>=1.5,3,IF(E17>=1,2,1))))*0.125*20)+(IF(E18>=10,5,IF(E18>=7,4,IF(E18>=5,3,IF(E18>=3,2,1))))*0.125*20) -> 81 | F21: =61+(IF(F17>=3,5,IF(F17>=2,4,IF(F17>=1.5,3,IF(F17>=1,2,1))))*0.125*20)+(IF(F18>=10,5,IF(F18>=7,4,IF(F18>=5,3,IF(F18>=3,2,1))))*0.125*20) -> 78.5 | H21: =48+(IF(H17>=3,5,IF(H17>=2,4,IF(H17>=1.5,3,IF(H17>=1,2,1))))*0.125*20)+(IF(H18>=10,5,IF(H18>=7,4,IF(H18>=5,3,IF(H18>=3,2,1))))*0.125*20) -> 68 | I21: =48+(IF(I17>=3,5,IF(I17>=2,4,IF(I17>=1.5,3,IF(I17>=1,2,1))))*0.125*20)+(IF(I18>=10,5,IF(I18>=7,4,IF(I18>=5,3,IF(I18>=3,2,1))))*0.125*20) -> 68 | J21: =48+(IF(J17>=3,5,IF(J17>=2,4,IF(J17>=1.5,3,IF(J17>=1,2,1))))*0.125*20)+(IF(J18>=10,5,IF(J18>=7,4,IF(J18>=5,3,IF(J18>=3,2,1))))*0.125*20) -> 68 | K21: =48+(IF(K17>=3,5,IF(K17>=2,4,IF(K17>=1.5,3,IF(K17>=1,2,1))))*0.125*20)+(IF(K18>=10,5,IF(K18>=7,4,IF(K18>=5,3,IF(K18>=3,2,1))))*0.125*20) -> 65.5 | L21: =48+(IF(L17>=3,5,IF(L17>=2,4,IF(L17>=1.5,3,IF(L17>=1,2,1))))*0.125*20)+(IF(L18>=10,5,IF(L18>=7,4,IF(L18>=5,3,IF(L18>=3,2,1))))*0.125*20) -> 63
A22: Stressed Risk Grade | B22: =IF(B21>=80,"AAA-AA",IF(B21>=65,"A-BBB",IF(B21>=50,"BB",IF(B21>=35,"B","CCC-D")))) -> AAA-AA | C22: =IF(C21>=80,"AAA-AA",IF(C21>=65,"A-BBB",IF(C21>=50,"BB",IF(C21>=35,"B","CCC-D")))) -> AAA-AA | D22: =IF(D21>=80,"AAA-AA",IF(D21>=65,"A-BBB",IF(D21>=50,"BB",IF(D21>=35,"B","CCC-D")))) -> AAA-AA | E22: =IF(E21>=80,"AAA-AA",IF(E21>=65,"A-BBB",IF(E21>=50,"BB",IF(E21>=35,"B","CCC-D")))) -> AAA-AA | F22: =IF(F21>=80,"AAA-AA",IF(F21>=65,"A-BBB",IF(F21>=50,"BB",IF(F21>=35,"B","CCC-D")))) -> A-BBB | H22: =IF(H21>=80,"AAA-AA",IF(H21>=65,"A-BBB",IF(H21>=50,"BB",IF(H21>=35,"B","CCC-D")))) -> A-BBB | I22: =IF(I21>=80,"AAA-AA",IF(I21>=65,"A-BBB",IF(I21>=50,"BB",IF(I21>=35,"B","CCC-D")))) -> A-BBB | J22: =IF(J21>=80,"AAA-AA",IF(J21>=65,"A-BBB",IF(J21>=50,"BB",IF(J21>=35,"B","CCC-D")))) -> A-BBB | K22: =IF(K21>=80,"AAA-AA",IF(K21>=65,"A-BBB",IF(K21>=50,"BB",IF(K21>=35,"B","CCC-D")))) -> A-BBB | L22: =IF(L21>=80,"AAA-AA",IF(L21>=65,"A-BBB",IF(L21>=50,"BB",IF(L21>=35,"B","CCC-D")))) -> BB
A23: Stressed IFRS 9 Stage | B23: =IF(B21>=65,"Stage 1",IF(B21>=50,"Stage 2",IF(B21>=35,"Stage 2/3","Stage 3"))) -> Stage 1 | C23: =IF(B21>=65,"Stage 1",IF(B21>=50,"Stage 2",IF(B21>=35,"Stage 2/3","Stage 3"))) -> Stage 1 | D23: =IF(B21>=65,"Stage 1",IF(B21>=50,"Stage 2",IF(B21>=35,"Stage 2/3","Stage 3"))) -> Stage 1 | E23: =IF(B21>=65,"Stage 1",IF(B21>=50,"Stage 2",IF(B21>=35,"Stage 2/3","Stage 3"))) -> Stage 1 | F23: =IF(B21>=65,"Stage 1",IF(B21>=50,"Stage 2",IF(B21>=35,"Stage 2/3","Stage 3"))) -> Stage 1 | H23: =IF(H21>=65,"Stage 1",IF(H21>=50,"Stage 2",IF(H21>=35,"Stage 2/3","Stage 3"))) -> Stage 1 | I23: =IF(I21>=65,"Stage 1",IF(I21>=50,"Stage 2",IF(I21>=35,"Stage 2/3","Stage 3"))) -> Stage 1 | J23: =IF(J21>=65,"Stage 1",IF(J21>=50,"Stage 2",IF(J21>=35,"Stage 2/3","Stage 3"))) -> Stage 1 | K23: =IF(K21>=65,"Stage 1",IF(K21>=50,"Stage 2",IF(K21>=35,"Stage 2/3","Stage 3"))) -> Stage 1 | L23: =IF(L21>=65,"Stage 1",IF(L21>=50,"Stage 2",IF(L21>=35,"Stage 2/3","Stage 3"))) -> Stage 2
A24: Stressed PD | B24: =IF(B22="AAA-AA",0.0003,IF(B22="A-BBB",0.0015,IF(B22="BB",0.02,IF(B22="B",0.08,0.2)))) -> 0.0003 | C24: =IF(C22="AAA-AA",0.0003,IF(C22="A-BBB",0.0015,IF(C22="BB",0.02,IF(C22="B",0.08,0.2)))) -> 0.0003 | D24: =IF(D22="AAA-AA",0.0003,IF(D22="A-BBB",0.0015,IF(D22="BB",0.02,IF(D22="B",0.08,0.2)))) -> 0.0003 | E24: =IF(E22="AAA-AA",0.0003,IF(E22="A-BBB",0.0015,IF(E22="BB",0.02,IF(E22="B",0.08,0.2)))) -> 0.0003 | F24: =IF(F22="AAA-AA",0.0003,IF(F22="A-BBB",0.0015,IF(F22="BB",0.02,IF(F22="B",0.08,0.2)))) -> 0.0015 | H24: =IF(H22="AAA-AA",0.0003,IF(H22="A-BBB",0.0015,IF(H22="BB",0.02,IF(H22="B",0.08,0.2)))) -> 0.0015 | I24: =IF(I22="AAA-AA",0.0003,IF(I22="A-BBB",0.0015,IF(I22="BB",0.02,IF(I22="B",0.08,0.2)))) -> 0.0015 | J24: =IF(J22="AAA-AA",0.0003,IF(J22="A-BBB",0.0015,IF(J22="BB",0.02,IF(J22="B",0.08,0.2)))) -> 0.0015 | K24: =IF(K22="AAA-AA",0.0003,IF(K22="A-BBB",0.0015,IF(K22="BB",0.02,IF(K22="B",0.08,0.2)))) -> 0.0015 | L24: =IF(L22="AAA-AA",0.0003,IF(L22="A-BBB",0.0015,IF(L22="BB",0.02,IF(L22="B",0.08,0.2)))) -> 0.02
A25: Stressed LGD | B25: =IF(B23="Stage 1",0.283,IF(B23="Stage 2",0.333,0.45)) -> 0.283 | C25: =IF(C23="Stage 1",0.283,IF(C23="Stage 2",0.333,0.45)) -> 0.283 | D25: =IF(D23="Stage 1",0.283,IF(D23="Stage 2",0.333,0.45)) -> 0.283 | E25: =IF(E23="Stage 1",0.283,IF(E23="Stage 2",0.333,0.45)) -> 0.283 | F25: =IF(F23="Stage 1",0.283,IF(F23="Stage 2",0.333,0.45)) -> 0.283 | H25: =IF(H23="Stage 1",0.308,IF(H23="Stage 2",0.358,0.45)) -> 0.308 | I25: =IF(I23="Stage 1",0.308,IF(I23="Stage 2",0.358,0.45)) -> 0.308 | J25: =IF(J23="Stage 1",0.308,IF(J23="Stage 2",0.358,0.45)) -> 0.308 | K25: =IF(K23="Stage 1",0.308,IF(K23="Stage 2",0.358,0.45)) -> 0.308 | L25: =IF(L23="Stage 1",0.308,IF(L23="Stage 2",0.358,0.45)) -> 0.358
A26: Stressed ECL USDM | B26: =720*B24*B25 -> 0.061128 | C26: =720*C24*C25 -> 0.061128 | D26: =720*D24*D25 -> 0.061128 | E26: =720*E24*E25 -> 0.061128 | F26: =720*F24*F25 -> 0.30564 | H26: =464*H24*H25 -> 0.214368 | I26: =464*I24*I25 -> 0.214368 | J26: =464*J24*J25 -> 0.214368 | K26: =464*K24*K25 -> 0.214368 | L26: =464*L24*L25 -> 3.32224
A27: ECL Change vs Base | B27: =B26-$B26 -> 0 | C27: =C26-B26 -> 0 | D27: =D26-C26 -> 0 | E27: =E26-D26 -> 0 | F27: =F26-E26 -> 0.244512 | H27: =H26-$H26 -> 0 | I27: =I26-H26 -> 0 | J27: =J26-I26 -> 0 | K27: =K26-J26 -> 0 | L27: =L26-K26 -> 3.107872

Sheet  Stress Test Assump
A2: Section 1 | P2: Key parameters (Assumptions)
A3: Macro Assumptions | B3: Base Case | C3: Scenario 1 High Oil | D3: Scenario 2 Low Oil | E3: Scenario 3 Cost pressure | F3: Scenario 4 Combined Severe | H3: Scenario 1
A4: Oil Price ($/bbl) | B4: 75 | C4: 144 | D4: 60 | E4: 90 | F4: 67 | H4: High Oil — based on current Brent crude at $96/bbl with recent intraweek spike to $144/bbl driven by escalating Middle East geopolitical tensions and OPEC+ supply constraints. Scenario reflects sustained price at recent peak levels.
A5: Revenue Change | B5: 0 | C5: 0.15 | D5: -0.2 | E5: -0.05 | F5: -0.25
A6: Cost Change % | B6: 0 | C6: 0.2 | D6: -0.1 | E6: 0.15 | F6: 0.2
A7: Interest Rate Change (bps) | B7: 0 | C7: 0 | D7: 0 | E7: 150 | F7: 200
A8: Freight/OpEx Change % | B8: 0 | C8: 0.1 | D8: 0 | E8: 0.3 | F8: 0.35
A9: FX Hedge Coverage % | B9: 0.5 | C9: 0.5 | D9: 0.5 | E9: 0.5 | F9: 0.5
A11: Section 2 | H11: Shell blended base LGD:
A12: Stressed Financials
A13: Base Revenue | H13: LC: 420 × 20% = 84
A14: Stressed Revenue | H14: TL: 300 × 40% = 120
A15: Base EBITDA | H15: Total exposure = 720
A16: Stressed EBITDA | H16: Blended LGD = (84+120)/720 = 28.3%
A17: Base Interest Expense
A18: Stressed Interest Expense | H18: BP blended base LGD:
A19: Stressed DSCR
A20: Stressed ICR | H20: LC: 264 × 20% = 52.8
H21: TL: 200 × 45% = 90
A22: Section 3 | H22: Total exposure = 464
A23: Stressed Scorecard Output | H23: Blended LGD = (52.8+90)/464 = 30.8%
A24: Stressed Risk Score
A25: Stressed Risk Grade | H25: Under stress LGD increases by 5% per stage deterioration:
A26: Stressed IFRS 9 Stage
A27: Stressed PD | H27: Stage 1: base
A28: Stressed LGD
A29: Stressed ECL USDM
